piperun/__init__.py
piperun/pipeline.py
piperun/shell.py
piperun/tasks.py
piperun/utils/logger.py
piperun-0.2.0.dist-info/METADATA
piperun-0.2.0.dist-info/WHEEL
piperun-0.2.0.dist-info/licenses/LICENSE
piperun-0.2.0.dist-info/RECORD
