Metadata-Version: 2.4
Name: piperun
Version: 0.2.0
Summary: A flexible framework for building and executing command pipelines in Python
Project-URL: Homepage, https://github.com/franioli/piperun
Project-URL: Documentation, https://github.com/franioli/piperun/
Project-URL: Repository, https://github.com/franioli/piperun
Author-email: Francesco Ioli <francesco.ioli@geo.uzh.ch>
Maintainer-email: Francesco Ioli <francesco.ioli@geo.uzh.ch>
License: MIT License
License-File: LICENSE
Keywords: command,parallel,pipeline,shell,task
Classifier: Development Status :: 3 - Alpha
Classifier: License :: OSI Approved :: MIT License
Classifier: Programming Language :: Python :: 3
Classifier: Topic :: Software Development :: Libraries :: Python Modules
Classifier: Topic :: System :: Shells
Requires-Python: >=3.8
Requires-Dist: dask[distributed]
Requires-Dist: graphviz
Provides-Extra: dev
Requires-Dist: bumpver; extra == 'dev'
Requires-Dist: mkdocs; extra == 'dev'
Requires-Dist: mkdocs-material; extra == 'dev'
Requires-Dist: mkdocstrings[python]; extra == 'dev'
Requires-Dist: pip-tools; extra == 'dev'
Requires-Dist: pre-commit; extra == 'dev'
Requires-Dist: pytest; extra == 'dev'
Requires-Dist: pytest-mock; extra == 'dev'
Requires-Dist: ruff; extra == 'dev'
